anonymizePy/__init__.py
anonymizePy/data_anonymization_toolkit.py
anonymizePy/resources/ignore_list.txt
anonymizePy/resources/states_list.txt
anonymizePy/resources/src/firstnames_list.txt
anonymizePy/resources/src/lastnames_list.txt
anonymizePy-0.1.6.dist-info/LICENSE
anonymizePy-0.1.6.dist-info/METADATA
anonymizePy-0.1.6.dist-info/WHEEL
anonymizePy-0.1.6.dist-info/top_level.txt
anonymizePy-0.1.6.dist-info/RECORD
