Metadata-Version: 2.1
Name: anonymizePy
Version: 0.1.6
Summary: A PII removal toolkit to help you anonymize your data.
Author-email: "Aussie D. Frost" <ausdfrost@gmail.com>
Project-URL: Homepage, https://github.com/ausdfrost/anonymizePy
Project-URL: Issues, https://github.com/ausdfrost/anonymizePy/issues
Classifier: Programming Language :: Python :: 3
Classifier: License :: OSI Approved :: MIT License
Classifier: Operating System :: OS Independent
Requires-Python: >=3.8
License-File: LICENSE
Requires-Dist: numpy >=1.9.3
Requires-Dist: pandas >=2.1.1
Requires-Dist: regex >=2.5.135
Requires-Dist: spacy >=3.4.4
Requires-Dist: scikit-learn >=0.24.0
